{
  "name": "@griffel/react",
  "entries": [
    {
      "date": "Wed, 09 Mar 2022 13:56:06 GMT",
      "tag": "@griffel/react_v1.0.2",
      "version": "1.0.2",
      "comments": {
        "patch": [
          {
            "author": "olfedias@microsoft.com",
            "package": "@griffel/react",
            "commit": "de373b3e85d3987a0b52b38df5f60d40ba9e6f22",
            "comment": "chore: add dependencies explicitly to package.json"
          },
          {
            "author": "beachball",
            "package": "@griffel/react",
            "comment": "Bump @griffel/core to v1.1.1",
            "commit": "7e1846070ad96b71b2789fe76e37dcac4f6155e7"
          }
        ]
      }
    },
    {
      "date": "Mon, 07 Mar 2022 09:08:08 GMT",
      "tag": "@griffel/react_v1.0.1",
      "version": "1.0.1",
      "comments": {
        "none": [
          {
            "author": "olfedias@microsoft.com",
            "package": "@griffel/react",
            "commit": "35ec68e5db45f33511b6091ad43eb2b3a316fa7b",
            "comment": "chore: add \"type-check\" target to project.json"
          },
          {
            "author": "lingfangao@hotmail.com",
            "package": "@griffel/react",
            "commit": "ff6078d3d9dac9a1d5310a027d41e7d6a75ce959",
            "comment": "chore: enable pretty type-check output"
          },
          {
            "author": "miroslav.stastny@microsoft.com",
            "package": "@griffel/react",
            "commit": "2d95ec00fb3a24e94c5bc1444d9f35ed42fe947f",
            "comment": "chore: add storybook to @griffel/react"
          },
          {
            "author": "miroslav.stastny@microsoft.com",
            "package": "@griffel/react",
            "commit": "ddcdb53a3d08613bda5a05d37720f36f42bcea7d",
            "comment": "chore: add DOMRenderer filter story"
          }
        ],
        "patch": [
          {
            "author": "olfedias@microsoft.com",
            "package": "@griffel/react",
            "commit": "225b54cb0f9ebcf2294e5a66b47dc45bfa13e813",
            "comment": "chore: add sourcemaps to dist files"
          }
        ]
      }
    },
    {
      "date": "Thu, 27 Jan 2022 13:47:55 GMT",
      "tag": "@griffel/react_v1.0.0",
      "version": "1.0.0",
      "comments": {
        "none": [
          {
            "author": "olfedias@microsoft.com",
            "package": "@griffel/react",
            "commit": "2d85e06323002984336d459bd36e0fa89cfa1b4e",
            "comment": "fix typos in README"
          }
        ]
      }
    },
    {
      "date": "Mon, 24 Jan 2022 09:32:24 GMT",
      "tag": "@griffel/react_v1.0.0",
      "version": "1.0.0",
      "comments": {
        "none": [
          {
            "author": "olfedias@microsoft.com",
            "package": "@griffel/react",
            "commit": "0a94e833bbc3a68276a52774d1de14d39a33635c",
            "comment": "fix lint issues"
          }
        ]
      }
    },
    {
      "date": "Thu, 20 Jan 2022 09:31:57 GMT",
      "tag": "@griffel/react_v1.0.0",
      "version": "1.0.0",
      "comments": {
        "major": [
          {
            "author": "olfedias@microsoft.com",
            "package": "@griffel/react",
            "commit": "3557c746fdd2c297aebfd6203bb3350a8f45bcf1",
            "comment": "initial release"
          }
        ]
      }
    }
  ]
}
